auxiliar/__init__.py
auxiliar-0.0.5.dist-info/METADATA
auxiliar-0.0.5.dist-info/WHEEL
auxiliar-0.0.5.dist-info/licenses/LICENSE
auxiliar-0.0.5.dist-info/RECORD
