Metadata-Version: 2.3
Name: auxiliar
Version: 0.0.5
Summary: Python helpers
Project-URL: Homepage, https://github.com/robertorussobob/auxiliar
Project-URL: Issues, https://github.com/robertorussobob/auxiliar/issues
Author-email: Roberto Russo <robertorussobob@gmail.com>
License-File: LICENSE
Classifier: Operating System :: OS Independent
Classifier: Programming Language :: Python :: 3
Requires-Python: >=3.8
